video2numpy/__init__.py
video2numpy/cli.py
video2numpy/frame_reader.py
video2numpy/read_vids_cv2.py
video2numpy/read_vids_ffmpeg.py
video2numpy/resizer.py
video2numpy/shared_queue.py
video2numpy/utils.py
video2numpy/video2numpy.py
video2numpy-2.3.3.data/data/README.md
video2numpy-2.3.3.dist-info/LICENSE
video2numpy-2.3.3.dist-info/METADATA
video2numpy-2.3.3.dist-info/WHEEL
video2numpy-2.3.3.dist-info/entry_points.txt
video2numpy-2.3.3.dist-info/top_level.txt
video2numpy-2.3.3.dist-info/RECORD
