Metadata-Version: 2.1
Name: video2numpy
Version: 2.3.3
Summary: Video reading into numpy
Home-page: https://github.com/iejMac/video2numpy
Author: Maciej Kilian
Author-email: kilianmaciej6@gmail.com
License: MIT
Keywords: machine learning
Platform: UNKNOWN
Classifier: Development Status :: 4 - Beta
Classifier: Intended Audience :: Developers
Classifier: Topic :: Scientific/Engineering :: Artificial Intelligence
Classifier: License :: OSI Approved :: MIT License
Classifier: Programming Language :: Python :: 3.6
Requires-Dist: numpy <2,>=1.19.5
Requires-Dist: fire <0.5.0,>=0.4.0
Requires-Dist: requests <3,>=2.27.1
Requires-Dist: ffmpeg-python
Requires-Dist: opencv-python
Requires-Dist: yt-dlp
